tetripin/__init__.py
tetripin/__main__.py
tetripin/tetripin.py
tetripin-0.1.1.dist-info/DESCRIPTION.rst
tetripin-0.1.1.dist-info/METADATA
tetripin-0.1.1.dist-info/RECORD
tetripin-0.1.1.dist-info/WHEEL
tetripin-0.1.1.dist-info/entry_points.txt
tetripin-0.1.1.dist-info/metadata.json
tetripin-0.1.1.dist-info/top_level.txt
