Metadata-Version: 2.0
Name: tetripin
Version: 0.1.1
Summary: 2FA manager
Home-page: UNKNOWN
Author: Tetricoins
Author-email: contact@tetricoins.com
License: MIT
Keywords: TOTP,2FA
Platform: UNKNOWN
Classifier: Development Status :: 1 - Planning
Classifier: Intended Audience :: Developers
Classifier: Natural Language :: English
Classifier: Programming Language :: Python :: 3
Classifier: Programming Language :: Python :: 3.7
Classifier: Operating System :: OS Independent
Requires-Dist: pyotp
Requires-Dist: toml
Requires-Dist: click
Requires-Dist: path.py
Requires-Dist: appdirs
